virt_stats/__init__.py
virt_stats/__main__.py
virt_stats-3.0.0.dist-info/METADATA
virt_stats-3.0.0.dist-info/WHEEL
virt_stats-3.0.0.dist-info/entry_points.txt
virt_stats-3.0.0.dist-info/top_level.txt
virt_stats-3.0.0.dist-info/RECORD
