Metadata-Version: 2.1
Name: virt_stats
Version: 3.0.0
Summary: This program is now deprecated.
Home-page: https://github.com/tidalmigrations/machine_stats
Author: Tidal
Author-email: support@tidalcloud.com
Requires-Dist: libvirt-python==7.3.0
